{
  "data": {
    "UK": {
      "Restaurant": {
        "Products": [
          {
            "period": 0,
            "items": [
              {
                "name": "Pro Online Ordering System",
                "product_id": "prod_PvxKyDfw97GWZl",
                "price_id": "UK1TRIAL",
                "currency": "gbp",
                "amount": 6900,
                "type": "solo",
                "status": "show",
                "ext": "/Month",
                "gst": false
              },
              {
                "name": "Add-on Only",
                "product_id": "prod_QhXCyNqi2nM0eI",
                "price_id": "AOT007UK",
                "currency": "gbp",
                "amount": 0,
                "type": "solo",
                "status": "show",
                "ext": "",
                "gst": false
              }
            ]
          },
          {
            "period": 3,
            "items": [
              {
                "name": "Social Media Marketing Bundle",
                "product_id": "prod_PvxKyDfw97GWZl",
                "price_id": "UK1TRIAL",
                "currency": "gbp",
                "amount": 15900,
                "type": "bundle",
                "status": "show",
                "ext": "/Month",
                "gst": false
              }
            ]
          },
          {
            "period": 12,
            "items": [
              {
                "name": "12 Months Pay Upfront - Pro Online Ordering System",
                "product_id": "prod_Q8z5xAS9p9zRxx",
                "price_id": "ROT063UK12",
                "currency": "gbp",
                "amount": 66240,
                "type": "solo",
                "status": "show",
                "ext": "/Month",
                "gst": false
              }
            ]
          }
        ],
        "Addons": {
          "Subscriptions": [
            {
              "period": "all",
              "items": [
              ]
            }
          ],
          "Onetime": [
            {
              "period": "all",
              "items": []
            }
          ],
          "Materials": [
            {
              "period": "all",
              "items": [
                {
                  "name": "A6 Flyers x 1,000 pcs",
                  "product_id": "prod_OL479AsMTDYV92",
                  "price_id": "AMA001UK",
                  "currency": "gbp",
                  "amount": 4500,
                  "type": "flyers",
                  "status": "show",
                  "ext": "",
                  "gst": false
                }
              ]
            }
          ],
          "Others": [
            {
              "period": "all",
              "items": []
            }
          ]
        }
      },
      "Massage": {
        "Products": [
          {
            "period": 0,
            "items": [
              {
                "name": "Localforyou Booking System (Incl Website Hosting and Booking System)",
                "product_id": "prod_PvxKyDfw97GWZl",
                "price_id": "UK1TRIAL",
                "currency": "gbp",
                "amount": 6900,
                "type": "solo",
                "status": "show",
                "ext": "/Month",
                "gst": false
              },
              {
                "name": "Add-on Only",
                "product_id": "prod_QhXCyNqi2nM0eI",
                "price_id": "AOT007UK",
                "currency": "gbp",
                "amount": 0,
                "type": "solo",
                "status": "show",
                "ext": "",
                "gst": false
              }
            ]
          },
          {
            "period": 3,
            "items": [
              {
                "name": "Social Media Marketing Bundle",
                "product_id": "prod_PvxKyDfw97GWZl",
                "price_id": "UK1TRIAL",
                "currency": "gbp",
                "amount": 15900,
                "type": "bundle",
                "status": "show",
                "ext": "/Month",
                "gst": false
              }
            ]
          }
        ],
        "Addons": {
          "Subscriptions": [
            {
              "period": "all",
              "items": [
              ]
            }
          ],
          "Onetime": [
            {
              "period": "all",
              "items": []
            }
          ],
          "Materials": [
            {
              "period": "all",
              "items": [
                {
                  "name": "A6 Flyers x 1,000 pcs",
                  "product_id": "prod_OL479AsMTDYV92",
                  "price_id": "AMA001UK",
                  "currency": "gbp",
                  "amount": 4500,
                  "type": "flyers",
                  "status": "show",
                  "ext": "",
                  "gst": false
                }
              ]
            }
          ],
          "Others": [
            {
              "period": "all",
              "items": []
            }
          ]
        }
      },
      "All": {
        "Products": [
          {
            "period": 0,
            "items": []
          }
        ],
        "Addons": {
          "Subscriptions": [
            {
              "period": "all",
              "items": [
                {
                  "name": "Social Media Management (2 x Mthly FB/Insta + GMB)",
                  "product_id": "prod_Q3msuILEJYVVUS",
                  "price_id": "AOT62UK",
                  "currency": "gbp",
                  "amount": 2900,
                  "type": "Management",
                  "status": "show",
                  "ext": "/Month",
                  "gst": false
              }
              ]
            }
          ],
          "Onetime": [
            {
              "period": "all",
              "items": []
            }
          ],
          "Materials": [
            {
              "period": "all",
              "items": []
            }
          ],
          "Others": [
            {
              "period": "all",
              "items": []
            }
          ]
        },
        "Special": {
          "SetupFee": [
            {
              "name": "Setup Fee (No Contract)",
              "product_id": "prod_QXLi2Yeo5CkUq9",
              "price_id": "AOT001UK",
              "currency": "gbp",
              "amount": 10900,
              "type": "setup",
              "status": "show",
              "ext": "",
              "gst": false
            }
          ]
        }
      }
    }
  },
  "object": "list"
}
